	[{
	  "Status": "Conflict Check Submitted",
	  "ResultId": 8668,
	  "ClientID": 105,
	  "ClientName": "vRisk Placeholder for Interim Period ",
	  "ProjectName": "12344321",
	  "AssessmentTypeName": "CC Pre-clearance",
	  "LastModifyDate": "08 Jun 2017",
	  "AssessmentUrl": "CCPre/DetailResult/105/8668"
	}, {
	  "Status": "Conflict Check Submitted",
	  "ResultId": 8669,
	  "ClientID": 105,
	  "ClientName": "vRisk Placeholder for Interim Period ",
	  "ProjectName": "12344231111",
	  "AssessmentTypeName": "CC Pre-clearance",
	  "LastModifyDate": "08 Jun 2017",
	  "AssessmentUrl": "CCPre/DetailResult/105/8669"
	}, {
	  "Status": "Draft",
	  "ResultId": 8677,
	  "ClientID": 105,
	  "ClientName": "vRisk Placeholder for Interim Period ",
	  "ProjectName": "N/A",
	  "AssessmentTypeName": "CC Pre-clearance",
	  "LastModifyDate": "13 Jun 2017",
	  "AssessmentUrl": "CCPre/DetailResult/105/8677"
	}, {
	  "Status": "Conflict Check Submitted",
	  "ResultId": 8678,
	  "ClientID": 105,
	  "ClientName": "vRisk Placeholder for Interim Period ",
	  "ProjectName": "1234",
	  "AssessmentTypeName": "CC Pre-clearance",
	  "LastModifyDate": "13 Jun 2017",
	  "AssessmentUrl": "CCPre/DetailResult/105/8678"
	}, {
	  "Status": "Conflict Check Submitted",
	  "ResultId": 8705,
	  "ClientID": 105,
	  "ClientName": "vRisk Placeholder for Interim Period ",
	  "ProjectName": "12341",
	  "AssessmentTypeName": "CC Pre-clearance",
	  "LastModifyDate": "21 Jun 2017",
	  "AssessmentUrl": "CCPre/DetailResult/105/8705"
	}, {
	  "Status": "Conflict Check Submitted",
	  "ResultId": 8706,
	  "ClientID": 105,
	  "ClientName": "vRisk Placeholder for Interim Period ",
	  "ProjectName": "112141",
	  "AssessmentTypeName": "CC Pre-clearance",
	  "LastModifyDate": "21 Jun 2017",
	  "AssessmentUrl": "CCPre/DetailResult/105/8706"
	}, {
	  "Status": "Conflict Check Submitted",
	  "ResultId": 8707,
	  "ClientID": 105,
	  "ClientName": "vRisk Placeholder for Interim Period ",
	  "ProjectName": "1",
	  "AssessmentTypeName": "CC Pre-clearance",
	  "LastModifyDate": "21 Jun 2017",
	  "AssessmentUrl": "CCPre/DetailResult/105/8707"
	}, {
	  "Status": "Conflict Check Submitted",
	  "ResultId": 8708,
	  "ClientID": 105,
	  "ClientName": "vRisk Placeholder for Interim Period ",
	  "ProjectName": "1",
	  "AssessmentTypeName": "CC Pre-clearance",
	  "LastModifyDate": "21 Jun 2017",
	  "AssessmentUrl": "CCPre/DetailResult/105/8708"
	}, {
	  "Status": "Conflict Check Submitted",
	  "ResultId": 8709,
	  "ClientID": 105,
	  "ClientName": "vRisk Placeholder for Interim Period ",
	  "ProjectName": "121",
	  "AssessmentTypeName": "CC Pre-clearance",
	  "LastModifyDate": "21 Jun 2017",
	  "AssessmentUrl": "CCPre/DetailResult/105/8709"
	}, {
	  "Status": "Conflict Check Submitted",
	  "ResultId": 8710,
	  "ClientID": 105,
	  "ClientName": "vRisk Placeholder for Interim Period ",
	  "ProjectName": "1121",
	  "AssessmentTypeName": "CC Pre-clearance",
	  "LastModifyDate": "21 Jun 2017",
	  "AssessmentUrl": "CCPre/DetailResult/105/8710"
	}, {
	  "Status": "Conflict Check Submitted",
	  "ResultId": 8718,
	  "ClientID": 105,
	  "ClientName": "vRisk Placeholder for Interim Period ",
	  "ProjectName": "Pre-CC",
	  "AssessmentTypeName": "CC Pre-clearance",
	  "LastModifyDate": "28 Jun 2017",
	  "AssessmentUrl": "CCPre/DetailResult/105/8718"
	}, {
	  "Status": "Conflict Check Submitted",
	  "ResultId": 8723,
	  "ClientID": 105,
	  "ClientName": "vRisk Placeholder for Interim Period ",
	  "ProjectName": "121",
	  "AssessmentTypeName": "CC Pre-clearance",
	  "LastModifyDate": "22 Jun 2017",
	  "AssessmentUrl": "CCPre/DetailResult/105/8723"
	}, {
	  "Status": "Draft",
	  "ResultId": 8738,
	  "ClientID": 105,
	  "ClientName": "vRisk Placeholder for Interim Period ",
	  "ProjectName": "N/A",
	  "AssessmentTypeName": "CC Pre-clearance",
	  "LastModifyDate": "23 Jun 2017",
	  "AssessmentUrl": "CCPre/DetailResult/105/8738"
	}, {
	  "Status": "Conflict Check Submitted",
	  "ResultId": 8749,
	  "ClientID": 105,
	  "ClientName": "vRisk Placeholder for Interim Period ",
	  "ProjectName": "121",
	  "AssessmentTypeName": "CC Pre-clearance",
	  "LastModifyDate": "28 Jun 2017",
	  "AssessmentUrl": "CCPre/DetailResult/105/8749"
	}, {
	  "Status": "Draft",
	  "ResultId": 8758,
	  "ClientID": 105,
	  "ClientName": "vRisk Placeholder for Interim Period ",
	  "ProjectName": "N/A",
	  "AssessmentTypeName": "CC Pre-clearance",
	  "LastModifyDate": "05 Jul 2017",
	  "AssessmentUrl": "CCPre/DetailResult/105/8758"
	}, {
	  "Status": "Conflict Check Submitted",
	  "ResultId": 8762,
	  "ClientID": 105,
	  "ClientName": "vRisk Placeholder for Interim Period ",
	  "ProjectName": "1231",
	  "AssessmentTypeName": "CC Pre-clearance",
	  "LastModifyDate": "07 Jul 2017",
	  "AssessmentUrl": "CCPre/DetailResult/105/8762"
	}, {
	  "Status": "Draft",
	  "ResultId": 8764,
	  "ClientID": 105,
	  "ClientName": "vRisk Placeholder for Interim Period ",
	  "ProjectName": "N/A",
	  "AssessmentTypeName": "CC Pre-clearance",
	  "LastModifyDate": "07 Jul 2017",
	  "AssessmentUrl": "CCPre/DetailResult/105/8764"
	}, {
	  "Status": "Draft",
	  "ResultId": 8767,
	  "ClientID": 105,
	  "ClientName": "vRisk Placeholder for Interim Period ",
	  "ProjectName": "N/A",
	  "AssessmentTypeName": "CC Pre-clearance",
	  "LastModifyDate": "10 Jul 2017",
	  "AssessmentUrl": "CCPre/DetailResult/105/8767"
	}, {
	  "Status": "Draft",
	  "ResultId": 8770,
	  "ClientID": 105,
	  "ClientName": "vRisk Placeholder for Interim Period ",
	  "ProjectName": "N/A",
	  "AssessmentTypeName": "CC Pre-clearance",
	  "LastModifyDate": "17 Jul 2017",
	  "AssessmentUrl": "CCPre/DetailResult/105/8770"
	}, {
	  "Status": "Completed",
	  "ResultId": 8771,
	  "ClientID": 105,
	  "ClientName": "vRisk Placeholder for Interim Period ",
	  "ProjectName": "121",
	  "AssessmentTypeName": "CC Pre-clearance",
	  "LastModifyDate": "17 Jul 2017",
	  "AssessmentUrl": "CCPre/DetailResult/105/8771"
	}]
